[{"level":"a1","name":"Hungarian A1 · 250 common words","source":"freq+freedict","cards":[{"front":"nem","back":"nope; nothing doing; nae"},{"front":"az","back":"it; that; the"},{"front":"hogy","back":"how; that; as"},{"front":"és","back":"and; plus; more"},{"front":"egy","back":"an; number one; single"},{"front":"van","back":"it is; to exist; have subsistence"},{"front":"ez","back":"this"},{"front":"is","back":"eke; also; too"},{"front":"de","back":"but"},{"front":"meg","back":"more; added to; and"},{"front":"csak","back":"but; only; just"},{"front":"ha","back":"an; and; if"},{"front":"mi","back":"what; we"},{"front":"én","back":"me; ego; i"},{"front":"azt","back":"which; it"},{"front":"volt","back":"volt; ex; late"},{"front":"igen","back":"high; aye; passing"},{"front":"vagy","back":"or; else"},{"front":"kell","back":"must; to require; got to"},{"front":"el","back":"off; aside; past"},{"front":"itt","back":"here; down here; herein"},{"front":"már","back":"before; yet; already"},{"front":"még","back":"some more; yet; more"},{"front":"te","back":"thou; ye"},{"front":"ki","back":"out; forth; off"},{"front":"mit","back":"what"},{"front":"most","back":"at present; this time; presently"},{"front":"jó","back":"fucking; near; guileless"},{"front":"úgy","back":"so"},{"front":"miért","back":"wherefore; why"},{"front":"akkor","back":"now; then; at this moment"},{"front":"mint","back":"as; like"},{"front":"jól","back":"right; for fair; nicely"},{"front":"nagyon","back":"very; bloody; bally"},{"front":"nincs","back":"to want; nae"},{"front":"mert","back":"sith; since"},{"front":"minden","back":"each; everything; all"},{"front":"sem","back":"neither"},{"front":"amit","back":"what; which; that"},{"front":"olyan","back":"such; as; so"},{"front":"rendben","back":"ship-shape"},{"front":"így","back":"accordingly; like this; in this manner"},{"front":"be","back":"on; inboard"},{"front":"nekem","back":"for me; me; to me"},{"front":"le","back":"off; below; down"},{"front":"fel","back":"over; up"},{"front":"tudod","back":"don`t you know"},{"front":"ott","back":"over there; over yonder; out there"},{"front":"lehet","back":"may"},{"front":"valami","back":"aught; some; something or other"},{"front":"majd","back":"then"},{"front":"mindig","back":"at all times; ever; always"},{"front":"talán","back":"probably; mayhap; perchance"},{"front":"maga","back":"herself; selves; oneself"},{"front":"köszönöm","back":"thanks; thank ye"},{"front":"semmi","back":"nullity; aught; sod all"},{"front":"hát","back":"why; now; back"},{"front":"aki","back":"he that; he who; that"},{"front":"hol","back":"where"},{"front":"neki","back":"it"},{"front":"szóval","back":"in one word; in words; in a word"},{"front":"neked","back":"thee; ye"},{"front":"ami","back":"which; what; that"},{"front":"kis","back":"little; low; small"},{"front":"tényleg","back":"in reality; truly; indeed"},{"front":"elég","back":"to burn out; no more; sufficient"},{"front":"fog","back":"to grab at; to grab; to grab for"},{"front":"igaz","back":"honest-to-god; truthful; fast"},{"front":"vele","back":"withal; along"},{"front":"milyen","back":"what kind of; what"},{"front":"ilyen","back":"such; of this kind; of the sort"},{"front":"ide","back":"hither; here"},{"front":"biztos","back":"firm; secure; positive"},{"front":"uram","back":"sirrah; sire"},{"front":"vissza","back":"aback; back"},{"front":"nagy","back":"power; grand; roomy"},{"front":"ma","back":"period; the day; today"},{"front":"egész","back":"total; fairly; round"},{"front":"nos","back":"why; well"},{"front":"vannak","back":"there are"},{"front":"azért","back":"wherefore; thence; thereupon"},{"front":"ember","back":"wallah; walla; bod"},{"front":"persze","back":"of course; certes; certainly"},{"front":"túl","back":"across; too; beyond"},{"front":"sok","back":"scores; a number of; much"},{"front":"két","back":"two"},{"front":"szia","back":"hi"},{"front":"valaki","back":"fellow; person; somebody or other"},{"front":"ahogy","back":"as"},{"front":"aztán","back":"in the sequel; whereabout; then"},{"front":"pedig","back":"now; in turn"},{"front":"engem","back":"me"},{"front":"ezért","back":"for this end; for this; with this object"},{"front":"velem","back":"with me"},{"front":"arra","back":"out there; that way"},{"front":"őt","back":"it"},{"front":"új","back":"second; new; unused"},{"front":"más","back":"else; other; unlike"},{"front":"semmit","back":"nothing"},{"front":"benne","back":"therein"},{"front":"se","back":"neither"},{"front":"szerintem","back":"to my mind; in my sight"},{"front":"miatt","back":"with; on account of; through"},{"front":"kérem","back":"prithee"},{"front":"jobb","back":"preferable; right; dexter"},{"front":"veled","back":"thee"},{"front":"erre","back":"upon this; thereupon; hither"},{"front":"több","back":"some; several; plus"},{"front":"baj","back":"misery; misadventure; harm"},{"front":"mindenki","back":"each; all ranks; one and all"},{"front":"soha","back":"never; at no; at no time"},{"front":"nap","back":"day; term; sun"},{"front":"akar","back":"to like; to want; to will"},{"front":"magát","back":"oneself; herself"},{"front":"együtt","back":"in conjunction with; along with; together"},{"front":"senki","back":"none; devil a one; nobody"},{"front":"szép","back":"nice-looking; proper; fair"},{"front":"át","back":"across; over; through"},{"front":"első","back":"prime; primary; leading"},{"front":"mintha","back":"as if; an; and"},{"front":"pár","back":"pair; couple"},{"front":"rossz","back":"evil; dirty; vicious"},{"front":"este","back":"vesper; night; sundown"},{"front":"ezek","back":"these"},{"front":"után","back":"past; after"},{"front":"emberek","back":"folk; all flesh; people"},{"front":"téged","back":"thee; ye"},{"front":"szerint","back":"in; according to; under"},{"front":"hogyan","back":"how"},{"front":"újra","back":"afresh; anew; again"},{"front":"kellene","back":"ought"},{"front":"dolog","back":"business; matter; part"},{"front":"egyszer","back":"on one occasion"},{"front":"annyira","back":"so; that; so much"},{"front":"igazán","back":"really; honour bright; true"},{"front":"oda","back":"up; there; thither"},{"front":"amíg","back":"until; so long as; whereas"},{"front":"másik","back":"second; other one; other"},{"front":"apa","back":"parent; governor; father"},{"front":"egyik","back":"one; either of them; either"},{"front":"tűnik","back":"to seem; to sound; to look"},{"front":"lett","back":"latvian"},{"front":"néhány","back":"several; one or two; some"},{"front":"inkább","back":"rather; preferably; more"},{"front":"jobban","back":"better; more"},{"front":"anya","back":"mother; parent; queen"},{"front":"saját","back":"respective; own; personal"},{"front":"rajta","back":"atop; on there"},{"front":"ezzel","back":"with this; with that"},{"front":"épp","back":"just"},{"front":"alatt","back":"underneath; pending; in"},{"front":"ebben","back":"in this; therein; herein"},{"front":"úr","back":"sahib; sirrah; master card"},{"front":"legjobb","back":"optimum; prime; tiptop"},{"front":"teljesen","back":"exhaustively; sheer; regularly"},{"front":"tud","back":"to savvy; to ken"},{"front":"magad","back":"thyself"},{"front":"három","back":"three"},{"front":"egyetlen","back":"single; only; one"},{"front":"megy","back":"to pass; to walk; to tend"},{"front":"jön","back":"to come to; to come on"},{"front":"mielőtt","back":"or; ere"},{"front":"szó","back":"word; term"},{"front":"mind","back":"each; every one; all"},{"front":"egyedül","back":"by oneself; single-handedly; single-handed"},{"front":"menjünk","back":"let`s get going; let`s go"},{"front":"komolyan","back":"sore; sincerely; severely"},{"front":"micsoda","back":"what"},{"front":"isten","back":"supreme being; godhead; divinity"},{"front":"mire","back":"whereof; whereon"},{"front":"tovább","back":"further; forth; any further"},{"front":"előtt","back":"or; ago; in front of"},{"front":"vége","back":"over; the end; out"},{"front":"ahol","back":"whereabout; whereabouts"},{"front":"holnap","back":"tomorrow"},{"front":"nő","back":"to grow large; to augment; to spring up"},{"front":"nélkül","back":"wanting; without; sine"},{"front":"ennek","back":"for this; of this; to this"},{"front":"tehát","back":"thus; so; accordingly"},{"front":"pontosan","back":"accurately; regularly; true"},{"front":"áll","back":"to endure; to stagnate; to hold good"},{"front":"először","back":"first; at first"},{"front":"mégis","back":"still; however; after all"},{"front":"remek","back":"top notch; crackajack; sniffy"},{"front":"idő","back":"period; weather; spell"},{"front":"megint","back":"again; to admonish"},{"front":"haver","back":"bucko; pal; sort"},{"front":"nehéz","back":"effortful; laborious; thorny"},{"front":"rád","back":"thee"},{"front":"lány","back":"fille; bint; wool"},{"front":"gyorsan","back":"with dispatch; volubly; rapidly"},{"front":"remélem","back":"i hope so"},{"front":"ti","back":"ye"},{"front":"hanem","back":"but"},{"front":"pont","back":"plumb; score; full"},{"front":"igazi","back":"pure; tangible; very"},{"front":"haza","back":"kith; country; home"},{"front":"utolsó","back":"last; ultimate; extreme"},{"front":"később","back":"later; in after years; in the sequel"},{"front":"mivel","back":"since; as; inasmuch as"},{"front":"megvan","back":"to inhere"},{"front":"ezen","back":"this"},{"front":"miről","back":"whereof"},{"front":"ennyi","back":"that much; so many; this much"},{"front":"legalább","back":"full; but; at least"},{"front":"azonnal","back":"straight on end; straightway; in a trice"},{"front":"magának","back":"oneself"},{"front":"sokkal","back":"a good deal; far; ever so much"},{"front":"férfi","back":"boyo; he; gent"},{"front":"tegnap","back":"yesterday"},{"front":"bele","back":"therein; into"},{"front":"fontos","back":"to matter; deep; operative"},{"front":"srácok","back":"small fry"},{"front":"akit","back":"that; whom"},{"front":"kedves","back":"likable; loving; bland"},{"front":"arról","back":"thereof"},{"front":"nagyszerű","back":"ace; wizard; magnificent"},{"front":"végre","back":"at long last; at last"},{"front":"gond","back":"trouble; snag; care"},{"front":"érdekel","back":"to interest; to concern; to intrigue"},{"front":"annak","back":"it"},{"front":"azon","back":"thereon"},{"front":"reggel","back":"morrow; at day; morning"},{"front":"többet","back":"moe; better"},{"front":"tetszik","back":"to list; to please; to like"},{"front":"attól","back":"thereon; therefrom"},{"front":"kész","back":"willing; made; bound"},{"front":"összes","back":"total; all; complete"},{"front":"ment","back":"to exculpate"},{"front":"helyzet","back":"state of affairs; lay; occasion"},{"front":"többé","back":"anymore; more"},{"front":"abba","back":"therein"},{"front":"néha","back":"sometimes; now and then; now and again"},{"front":"meghalt","back":"dead and gone; to be gone; he`s dead"},{"front":"biztosan","back":"certainly; without peradventure; securely"},{"front":"egyáltalán","back":"aught; at all; in the world"},{"front":"néz","back":"to watch; to eyeball; to screw"},{"front":"halott","back":"dead; goner; gone"},{"front":"boldog","back":"happy; beaming; sunny"},{"front":"következő","back":"next; ensuing; succeeding"},{"front":"hely","back":"dump; corner; spot"},{"front":"képes","back":"susceptible; able; capable"},{"front":"számít","back":"to signify; to hope; to count"},{"front":"között","back":"amid; among; twixt"},{"front":"abban","back":"therein"},{"front":"régi","back":"pristine; olden; time-worn"},{"front":"fickó","back":"cuss; fellow; coon"},{"front":"óta","back":"sith; since; downwards"},{"front":"jelent","back":"to constitute; to imply; to report"},{"front":"történik","back":"to betide; to pass; to happen"}]},{"level":"a2","name":"Hungarian A2 · 245 common words","source":"freq+freedict","cards":[{"front":"mond","back":"to term; to pronounce; to impart"},{"front":"tiszta","back":"pure; sinless; unexceptional"},{"front":"otthon","back":"in doors; fireside; within doors"},{"front":"élet","back":"pep; living; subsistence"},{"front":"szól","back":"to call; to ring out; to yammer"},{"front":"hosszú","back":"long; long-drawn; prolonged"},{"front":"szépen","back":"beautifully; handsomely; fine"},{"front":"hangzik","back":"to sound; to ring out"},{"front":"helyes","back":"seemly; compt; legitimate"},{"front":"bocs","back":"ball"},{"front":"mást","back":"other"},{"front":"közel","back":"nearly; by near; near"},{"front":"ötlet","back":"idea; flash of wit; brainchild"},{"front":"viszont","back":"however; conversely; then again"},{"front":"tart","back":"to reckon; to cultivate; to bear"},{"front":"ok","back":"begetter; score; cause"},{"front":"végül","back":"last; lastly; in fine"},{"front":"halló","back":"hallo; aural; halloa"},{"front":"hamarosan","back":"soon; ere long; before long"},{"front":"jár","back":"to spook; to step; to gang"},{"front":"bocsánat","back":"pardon; forgiveness; remission"},{"front":"doktor","back":"doctor"},{"front":"hét","back":"week; seven"},{"front":"furcsa","back":"dutch; fantastic; extraordinary"},{"front":"alig","back":"barely; scantily; sparingly"},{"front":"egymást","back":"one another; each other"},{"front":"többi","back":"other"},{"front":"korábban","back":"beforehand; previously; ci-devant"},{"front":"muszáj","back":"have got to; got to; ought"},{"front":"vagyis","back":"namely; that is; in one word"},{"front":"rosszul","back":"nohow; amiss; ill"},{"front":"sokáig","back":"for long; long"},{"front":"kurva","back":"whore; shag; harlot"},{"front":"hat","back":"to actuate; to take effect; to act"},{"front":"pillanat","back":"second; instant; jiffy"},{"front":"szívesen","back":"accommodatingly; readily; certainly"},{"front":"mellett","back":"past; by; beside"},{"front":"melyik","back":"which"},{"front":"marad","back":"to bide; to rest; to abide"},{"front":"eltűnt","back":"missing; legally dead; withered"},{"front":"rendőrség","back":"police force; constabulary; police"},{"front":"beteg","back":"ailing; to be ill; ill"},{"front":"srác","back":"urchin; yob; yobbo"},{"front":"ennyire","back":"that rate; this rate; so much"},{"front":"második","back":"second; number two; follow-up"},{"front":"különleges","back":"particular; special; original"},{"front":"gyerekek","back":"small fry; chillun; children"},{"front":"működik","back":"to pan; to operate; to function"},{"front":"magával","back":"along"},{"front":"ügy","back":"affair; go; shower of shit"},{"front":"kérdés","back":"issue; query; point"},{"front":"komoly","back":"civil; demure; severe"},{"front":"él","back":"point; to exist; to subsist"},{"front":"keresztül","back":"via; aslant; through"},{"front":"akinek","back":"whom"},{"front":"egyszerű","back":"humble; rustic; unpretending"},{"front":"őrült","back":"crackpot; insensate; whacky"},{"front":"dolgozik","back":"to labour; to pant; to labor"},{"front":"hívják","back":"to be wanted"},{"front":"felé","back":"on; toward; to"},{"front":"erős","back":"sharp; stalwart; broad"},{"front":"belül","back":"on the inside; in; within"},{"front":"fehér","back":"fair; hoar; white"},{"front":"fekete","back":"sooty; sable; darkey"},{"front":"csodálatos","back":"prodigious; noble; wondrous"},{"front":"annyit","back":"as much"},{"front":"lehetséges","back":"probable; possible; likely"},{"front":"mindketten","back":"we both"},{"front":"gyilkos","back":"carnal; bloody; death-dealing"},{"front":"alá","back":"underneath; under; beneath"},{"front":"édes","back":"sweet; suave; ducky"},{"front":"amire","back":"whereof; wherewithal; whereupon"},{"front":"vár","back":"to expect; to await; to hang fire"},{"front":"hatalmas","back":"overpowering; mighty; gigantesque"},{"front":"mindegy","back":"just the same; it`s all one"},{"front":"fiatal","back":"juvenile; young; tender"},{"front":"igazság","back":"right; truth; veraciousness"},{"front":"kibaszott","back":"fucking"},{"front":"közben","back":"a-; midst of; betwixt"},{"front":"bárki","back":"any; anybody; whoever"},{"front":"kettő","back":"number two; two; twain"},{"front":"nagyobb","back":"superior; more; major"},{"front":"fene","back":"dickens; heck; deuce"},{"front":"úton","back":"in transit; underway; under sail"},{"front":"segítség","back":"auxiliary; support; aid"},{"front":"múlt","back":"past; last; bygone"},{"front":"érdekes","back":"interesting; juicy; readable"},{"front":"könnyű","back":"flimsy; easy; of light weight"},{"front":"szörnyű","back":"unholy; awful; atrocious"},{"front":"uraim","back":"my masters"},{"front":"segít","back":"to succour; to speed; to minister"},{"front":"kívül","back":"without; beyond; to judge"},{"front":"előre","back":"beforehand; up front; forward"},{"front":"asszonyom","back":"mum"},{"front":"amiért","back":"whereat; wherefore"},{"front":"különben","back":"for the rest; otherwise; failing which"},{"front":"valahol","back":"anywhere; someplace"},{"front":"elnök","back":"president; chairman; chair"},{"front":"hány","back":"to dump; to puke; to throw up"},{"front":"probléma","back":"proposition; question; problem"},{"front":"ügynök","back":"drummer; mole; goer between"},{"front":"máris","back":"right off; right away"},{"front":"esetleg","back":"mayhap; by accident; mayhaps"},{"front":"egyre","back":"time and again; ever"},{"front":"tele","back":"full; replete; thick with"},{"front":"tesz","back":"to refer; to put in; to bestow"},{"front":"egészen","back":"fairly; over; totally"},{"front":"mondjuk","back":"shall we say; let us say; say"},{"front":"legnagyobb","back":"paramount; outside; extreme"},{"front":"nyomozó","back":"tail; investigatory; tracer"},{"front":"bent","back":"within; ben; in"},{"front":"tíz","back":"dicker; ten"},{"front":"például","back":"shell i say; say; for instance"},{"front":"titeket","back":"ye"},{"front":"család","back":"folks; people; house"},{"front":"veszélyes","back":"fraught with danger; hairy; risky"},{"front":"meleg","back":"fag; rich; to be warm"},{"front":"ér","back":"to hit; kill; seam"},{"front":"halál","back":"passing; death; fate"},{"front":"kicsi","back":"pygmy; scrimp; slight"},{"front":"szent","back":"hieratic; saint; holy"},{"front":"ház","back":"theatre; housing; home"},{"front":"édesem","back":"luv"},{"front":"adott","back":"given"},{"front":"hozzád","back":"thee; to thee"},{"front":"eléggé","back":"fairly; tolerable; rather"},{"front":"szükség","back":"exigency; exigence; want"},{"front":"újabb","back":"subsequent; late"},{"front":"mai","back":"recent; modern; present-day"},{"front":"fáj","back":"to ache; to smart; to give pain"},{"front":"régen","back":"long ago; aforetime; long since"},{"front":"kemény","back":"sharp; severe; firm"},{"front":"rengeteg","back":"world of; mort; lashings"},{"front":"látszik","back":"to show up; to seem; to sound"},{"front":"amerikai","back":"stateside; american"},{"front":"körül","back":"about; round about; toward"},{"front":"rohadt","back":"damned; stinky; blankety-blank"},{"front":"kerül","back":"to balk; to get into; to come out"},{"front":"éjszaka","back":"night-time; at night-time; night"},{"front":"valahogy","back":"kind of; sort of; somehow"},{"front":"hirtelen","back":"snap; all at once; overnight"},{"front":"rögtön","back":"pronto; instanter; straight away"},{"front":"barátok","back":"kith"},{"front":"végig","back":"out; all over; till the last"},{"front":"ért","back":"to catch on; to savvy"},{"front":"biztonsági","back":"splinter-proof; protecting; splinterless"},{"front":"egyébként","back":"for another thing; for the rest; again"},{"front":"anyu","back":"mum; mom; mommy"},{"front":"szar","back":"sleazy; dipshit; muck"},{"front":"vajon","back":"whether"},{"front":"hisz","back":"to calculate; to trust; to believe"},{"front":"szegény","back":"poor; penniless; hungry"},{"front":"nektek","back":"ye"},{"front":"érzés","back":"sense; sentiment; feeling"},{"front":"frank","back":"frank; franc; frankian"},{"front":"okos","back":"conceited; brainy; sophisticated"},{"front":"út","back":"passage; ride; conduit"},{"front":"biztonságban","back":"scot-free"},{"front":"mögött","back":"behind; after"},{"front":"esküszöm","back":"on my oath"},{"front":"távol","back":"afar; way; far away"},{"front":"ugyanaz","back":"selfsame; same; do"},{"front":"sajnos","back":"sorry to say; unhappily; i am sorry"},{"front":"kölyök","back":"boyo; kiddie; kid"},{"front":"emberi","back":"human"},{"front":"szeretne","back":"to long; to wish"},{"front":"kint","back":"out"},{"front":"orvos","back":"medico; medical man; leech"},{"front":"csapat","back":"team; crowd; skein"},{"front":"elmúlt","back":"last; to be over; to be up"},{"front":"gondol","back":"to opine; to figure; to conceive"},{"front":"késő","back":"late; tardy; belated"},{"front":"apu","back":"daddy; pap; dad"},{"front":"keres","back":"to look for; to pick up; to search"},{"front":"feleségem","back":"my old duchess"},{"front":"felesége","back":"his good lady"},{"front":"merre","back":"whither"},{"front":"folyton","back":"incessantly; always"},{"front":"mozgás","back":"cast; action; drift"},{"front":"rólad","back":"of thee"},{"front":"dollár","back":"buck; simoleon"},{"front":"legközelebb","back":"the next time; next time"},{"front":"hihetetlen","back":"wondrous; marvelous; unbelievable"},{"front":"kifelé","back":"outwards; out"},{"front":"fura","back":"rummy; rum; queer"},{"front":"város","back":"city; borough; place"},{"front":"itthon","back":"at home"},{"front":"szeret","back":"to relish; to like; to love"},{"front":"időben","back":"on time; in time"},{"front":"hátra","back":"backwards; astern; aback"},{"front":"idióta","back":"idiot; moron"},{"front":"városban","back":"down town; downtown"},{"front":"lassan","back":"slowly; adagio; unhurriedly"},{"front":"lehetetlen","back":"preposterous; it cannot be; beyond possibility"},{"front":"megfelelő","back":"equivalent; corresponding; suitable"},{"front":"víz","back":"water"},{"front":"szerelem","back":"crush; passion; mush"},{"front":"kivéve","back":"bated; saving; wanting"},{"front":"utoljára","back":"last"},{"front":"lényeg","back":"main thing; entity; main point"},{"front":"bizony","back":"verily; jolly well; to be sure"},{"front":"miközben","back":"in"},{"front":"hír","back":"information; tidings; buzz"},{"front":"alapján","back":"by"},{"front":"közül","back":"in; out; out of"},{"front":"őszintén","back":"outright; plain; genuinely"},{"front":"amivel","back":"wherewith; whereby"},{"front":"önt","back":"to dip; to pour; to found"},{"front":"azóta","back":"since then; thence; since that time"},{"front":"általában","back":"in general; upon the whole; in the main"},{"front":"végén","back":"in the end; terminally"},{"front":"nyugodtan","back":"unhurriedly; placidly; leisurely"},{"front":"drága","back":"costly; precious; dear"},{"front":"hiányzik","back":"to fault; to fail; to lack"},{"front":"bizonyos","back":"clear; particular; sure"},{"front":"egyes","back":"single; individual; some"},{"front":"jövő","back":"coming; future; futurity"},{"front":"kislány","back":"sissy; gal; girl"},{"front":"rész","back":"section; proportion; portion"},{"front":"azután","back":"thereafter; after; next"},{"front":"messze","back":"far away; way back; by all odds"},{"front":"csodás","back":"heavenly; divvy; wonderful"},{"front":"szemét","back":"sleaze; dreck; muck"},{"front":"hölgyem","back":"missus"},{"front":"föld","back":"clime; terra; earth"},{"front":"mostanában","back":"recently; lately; of late"},{"front":"csomó","back":"gnarl; bundle; bunch"},{"front":"szuper","back":"super; boss; sniffy"},{"front":"hívott","back":"yclept; ycleped"},{"front":"kezd","back":"to start; to throw off; to set in"},{"front":"titkos","back":"private; hugger-mugger; classified"},{"front":"büszke","back":"high-minded; supercilious; proud"},{"front":"magas","back":"high; piping; lofty"},{"front":"nők","back":"womanhood; sex; womenfolk"},{"front":"áldozat","back":"prey; sacrifice; victim"},{"front":"vér","back":"blood; life-blood"},{"front":"kap","back":"to procure; to receive; to be given"},{"front":"miféle","back":"what kind of"},{"front":"gonosz","back":"viperine; bad; ungodly"},{"front":"hiszen","back":"sith"},{"front":"normális","back":"normal; ornery; run"},{"front":"nyomás","back":"impression; pinch; press"},{"front":"terv","back":"plan; counsel; plot"},{"front":"mások","back":"others; other people"},{"front":"sötét","back":"saturnine; louring; shady"}]},{"level":"b1","name":"Hungarian B1 · 300 common words","source":"freq+freedict","cards":[{"front":"ám","back":"however"},{"front":"játék","back":"toy; slack; quiz"},{"front":"harmadik","back":"third"},{"front":"bíró","back":"adjudicator; justice; umpire"},{"front":"módon","back":"in"},{"front":"kissé","back":"poorly; slightly"},{"front":"hogyne","back":"definitely; certainly; certes"},{"front":"hála","back":"gratitude; indebtedness; thankfulness"},{"front":"tűz","back":"fire; firing; to zap"},{"front":"háború","back":"warfare; war"},{"front":"kutya","back":"dog"},{"front":"hadnagy","back":"lieutenant; shavetail; second lieutenant"},{"front":"közös","back":"corporate; joint; collective"},{"front":"jut","back":"to fall on; to get into; to fetch up"},{"front":"dühös","back":"sick; to be choked; hot"},{"front":"szerelmes","back":"amorous; flame; spoon"},{"front":"őszinte","back":"wholehearted; devout; honest"},{"front":"szinte","back":"next door to; as good as"},{"front":"hajó","back":"keel; ship; craft"},{"front":"fegyver","back":"weapon; arms; gun"},{"front":"hideg","back":"searching; sexless; metallic"},{"front":"valódi","back":"simon-pure; actual; intrinsical"},{"front":"ad","back":"to gift; to impart; to provide"},{"front":"óvatosan","back":"circumspectly; guardedly; gently"},{"front":"éhes","back":"to feel empty; eager; to be hungry"},{"front":"igenis","back":"yes; very good"},{"front":"személyes","back":"personal"},{"front":"szomorú","back":"piteous; sad; cheerless"},{"front":"hacsak","back":"whenever; but that; whensoever"},{"front":"jézus","back":"jesus"},{"front":"nevű","back":"-named"},{"front":"létezik","back":"to exist; to live; have subsistence"},{"front":"kíváncsi","back":"wondering; inquisitive; have itching ears"},{"front":"amiről","back":"whereabout; whereof"},{"front":"egyenesen","back":"forthrightly; straight; uprightly"},{"front":"kár","back":"disservice; damage; ill"},{"front":"szét","back":"asunder; apart"},{"front":"seggfej","back":"prat; fuckhead; dim-wit"},{"front":"bébi","back":"baby"},{"front":"vörös","back":"foxy; ruddy; red"},{"front":"baleset","back":"casualty; misadventure; accident"},{"front":"mama","back":"mother; mater; mommy"},{"front":"csupán","back":"simply; merely; only"},{"front":"tartozik","back":"to concern; to come under; to owe"},{"front":"ismét","back":"again; gin"},{"front":"szükséges","back":"needful; necessary; consequential"},{"front":"férje","back":"her good man"},{"front":"gyors","back":"snap; prompt; zippy"},{"front":"parancsnok","back":"commander; captain; leader"},{"front":"üres","back":"hollow; empty; expressionless"},{"front":"előző","back":"preceding; prior; afore"},{"front":"nyugalom","back":"calmness; quiescence; placidity"},{"front":"szemben","back":"vis-a-vis; oppositely; in front of"},{"front":"állandóan","back":"always; round the clock; constantly"},{"front":"emlékszik","back":"to remember"},{"front":"abból","back":"thereof; therefrom"},{"front":"gyakran","back":"again and again; oftentimes; many a time"},{"front":"bolond","back":"lightheaded; wacky; whacky"},{"front":"elé","back":"before"},{"front":"finom","back":"high-toned; mellow; snappy"},{"front":"kér","back":"to ask for; to demand; to pray"},{"front":"kék","back":"blue"},{"front":"világos","back":"articulate; clear; broad"},{"front":"régóta","back":"long ago; long since"},{"front":"kedvesem","back":"dearie; my dear; cony"},{"front":"kedvenc","back":"angel; bosom; pet"},{"front":"felség","back":"majesty; royalty"},{"front":"földön","back":"under feet"},{"front":"történet","back":"yarn; story"},{"front":"rendes","back":"proper; snug; trim"},{"front":"bármilyen","back":"odd; whatever; whatsoever"},{"front":"őrmester","back":"mess sergeant; sergeant"},{"front":"könnyen","back":"on a platter; effortlessly; readily"},{"front":"fantasztikus","back":"stupendous; kooky; screwy"},{"front":"ártatlan","back":"artless; guiltless; sinless"},{"front":"főleg","back":"in particular; chiefly; mostly"},{"front":"hozzánk","back":"to our house"},{"front":"hasonló","back":"cousin; akin; parallel"},{"front":"baba","back":"poppet; dolly; puppet"},{"front":"gyilkosság","back":"wipe; murder; hit"},{"front":"jelenleg","back":"now; currently; presently"},{"front":"hölgy","back":"dame; lady"},{"front":"lehetőség","back":"eventuality; opportunity; slant"},{"front":"fent","back":"high; up; above"},{"front":"átkozott","back":"blamed; accursed; bloody"},{"front":"többiek","back":"everybody else; rest; remainder"},{"front":"tábornok","back":"general; general officer"},{"front":"korán","back":"abortively; prematurely; soon"},{"front":"amely","back":"which; what"},{"front":"csinos","back":"crackajack; natty; smart"},{"front":"legtöbb","back":"utmost"},{"front":"kisasszony","back":"missy; miss"},{"front":"amiben","back":"wherein"},{"front":"ideges","back":"fazed; sore; neurotic"},{"front":"valamilyen","back":"a sort of"},{"front":"kocsi","back":"cart; coach; carrier"},{"front":"félre","back":"clear; apart; wide open"},{"front":"bizonyíték","back":"testimony; evidence; exhibit"},{"front":"keményen","back":"firmly; severely; hard"},{"front":"semmilyen","back":"none; no"},{"front":"sokan","back":"numbers; good many people; a great many"},{"front":"bármikor","back":"whenever; at all times; at all hours"},{"front":"kezdődik","back":"to set in; to commence; to start off"},{"front":"terhes","back":"irksome; childing; heavy"},{"front":"nappal","back":"time of day; by day; in the daytime"},{"front":"szerencsés","back":"apt; providential; gracious"},{"front":"asszony","back":"missus; hen; heifer"},{"front":"aranyos","back":"ducky; nice; cunning"},{"front":"ezredes","back":"colonel"},{"front":"közepén","back":"midst of"},{"front":"tök","back":"flat-out; dork; marrow"},{"front":"akiket","back":"whom"},{"front":"ellenére","back":"with; notwithstanding"},{"front":"ajtó","back":"door"},{"front":"földre","back":"down"},{"front":"nyolc","back":"eight"},{"front":"küldött","back":"emissary; deputy; envoy"},{"front":"véletlenül","back":"peradventure; haphazard; by any chance"},{"front":"óriási","back":"stupendous; vast; grandiose"},{"front":"mérges","back":"to be miffed; to be choked; surly"},{"front":"nevetséges","back":"harlequin; undignified; ridiculous"},{"front":"nálunk","back":"down our way; in our midst"},{"front":"hónap","back":"moon; month"},{"front":"rendőr","back":"police; blue-bottle; sleuth"},{"front":"remekül","back":"fine; wonderfully; like one o`clock"},{"front":"zsaru","back":"mug john; trap; copper"},{"front":"örökké","back":"always; ever; eternally"},{"front":"kiderült","back":"to be out"},{"front":"örökre","back":"for ever; world without end; for keeps"},{"front":"által","back":"by; through"},{"front":"közt","back":"amid; amidst"},{"front":"választ","back":"to opt; to cull; to embrace"},{"front":"mester","back":"master; maestro; governor"},{"front":"név","back":"denomination; designation; moniker"},{"front":"esik","back":"to come down; to land; to rain"},{"front":"orvosi","back":"medical"},{"front":"vált","back":"to change; to relay; to exchange"},{"front":"hű","back":"near; true; faithful"},{"front":"meghal","back":"to pass on; to cop it; to die"},{"front":"csaj","back":"moll; nookie; chippy"},{"front":"helyett","back":"vice; in place of"},{"front":"hiba","back":"vice; trip; bloomer"},{"front":"családi","back":"family; home"},{"front":"nevet","back":"to laugh; to pooh-pooh; to crack up"},{"front":"franc","back":"french disease; sucker"},{"front":"örömmel","back":"fain; gladly"},{"front":"börtönben","back":"in hock"},{"front":"különös","back":"bonkers; freaky; oddish"},{"front":"lakik","back":"to reside; to occupy; to inhabit"},{"front":"doki","back":"medic"},{"front":"férfiak","back":"menfolk; manhood"},{"front":"helyi","back":"local; topical; regional"},{"front":"önök","back":"your good selves"},{"front":"azelőtt","back":"previously; in olden times; in times past"},{"front":"testvér","back":"bud; sibling"},{"front":"biztonságos","back":"secure; safe; trouble-free"},{"front":"személy","back":"person; number; personality"},{"front":"fasz","back":"sucker; poker; prick"},{"front":"délután","back":"afternoon; in the afternoon"},{"front":"előtte","back":"afore"},{"front":"vezető","back":"guide; kingfish; governor"},{"front":"egyszerre","back":"at one go; all at once; together"},{"front":"ostoba","back":"wacky; peevish; dumbshit"},{"front":"némi","back":"something of; some; a measure of"},{"front":"üzlet","back":"go; buy; whiz"},{"front":"nehogy","back":"for fear of; lest"},{"front":"alkalom","back":"opportunity; break; peg"},{"front":"legalábbis","back":"leastways; leastwise; at any rate"},{"front":"gazdag","back":"fraught; affluent; well-to-do"},{"front":"lent","back":"down; under; below"},{"front":"kevés","back":"little; scarce; tight"},{"front":"vezet","back":"to govern; to rule; have the lead"},{"front":"egymás","back":"one another"},{"front":"rövid","back":"concise; compendious; succinct"},{"front":"hajlandó","back":"willing; ready; content"},{"front":"vicc","back":"jape; humour; droll"},{"front":"barát","back":"monk; friend; lover"},{"front":"különösen","back":"in particular; funnily; specially"},{"front":"don","back":"don"},{"front":"ezúttal","back":"this time"},{"front":"hamar","back":"soon"},{"front":"kapcsolat","back":"acquaintanceship; conjunction; association"},{"front":"min","back":"whereat"},{"front":"professzor","back":"professor; don"},{"front":"buli","back":"toot; bash; party"},{"front":"sőt","back":"nay; yes; moreover"},{"front":"nemsokára","back":"by and by; soon; ere long"},{"front":"papa","back":"governor; papa; pater"},{"front":"indulás","back":"offset; starting; setout"},{"front":"fáradt","back":"languid; tired; heavy"},{"front":"nővér","back":"nun; fille; nurse"},{"front":"sohasem","back":"never"},{"front":"gyenge","back":"flabby; low; faint"},{"front":"legrosszabb","back":"worst"},{"front":"autó","back":"automobile; tin lizzie; motor car"},{"front":"amin","back":"whereat; whereon"},{"front":"meglepetés","back":"astonishment; surprise; jolt"},{"front":"bal","back":"left; leftward"},{"front":"film","back":"pix; picture; screen"},{"front":"felett","back":"beyond; above; over"},{"front":"válasz","back":"answer; rejoinder; reply"},{"front":"figyelem","back":"interest; respect; heed"},{"front":"idegen","back":"stranger; strange; outlander"},{"front":"hal","back":"fish"},{"front":"túlságosan","back":"beyond measure; unduly; immoderately"},{"front":"szám","back":"number; badge; digit"},{"front":"ráadásul","back":"moreover; on the side; furthermore"},{"front":"hamis","back":"untrue; phony; double"},{"front":"különböző","back":"differing; distinct; unlike"},{"front":"női","back":"womanly; women`s; woman`s"},{"front":"félsz","back":"willies"},{"front":"érdekében","back":"in favour of"},{"front":"bajban","back":"in a spot"},{"front":"bizonyára","back":"certainly; in all conscience; in conscience"},{"front":"újság","back":"tidings; print; newness"},{"front":"hálás","back":"indebted; grateful; thankful"},{"front":"eljön","back":"to come away; to come along"},{"front":"mindenhol","back":"on all sides; from every side; near and far"},{"front":"szabadon","back":"freely; with impunity; without hindrance"},{"front":"személyesen","back":"in person; bodily; privately"},{"front":"csoda","back":"marvel; wonder; prodigy"},{"front":"iskola","back":"school"},{"front":"élő","back":"living being; have life; animated"},{"front":"igazgató","back":"guiding; governor; warden"},{"front":"ügyvéd","back":"stuff gownsman; attorney; legal practitioner"},{"front":"lenyűgöző","back":"grandiose; enthralling; compelling"},{"front":"kevesebb","back":"lesser; short; less"},{"front":"bátyám","back":"my elder brother"},{"front":"zöld","back":"green; verdant"},{"front":"valamire","back":"over something"},{"front":"hátsó","back":"hind; dorso-; posterior"},{"front":"családom","back":"my people; my folks"},{"front":"magától","back":"of oneself; spontaneously"},{"front":"klassz","back":"bang-up; crackerjack; cheese"},{"front":"híres","back":"illustrious; celebrated; hot"},{"front":"született","back":"born"},{"front":"vacsora","back":"supper; dinner"},{"front":"ingyen","back":"free of charge; for nothing; gratis"},{"front":"forró","back":"ebullient; fervid; torrid"},{"front":"írta","back":"written by"},{"front":"pasi","back":"sod; covey; fucker"},{"front":"pofa","back":"trap; kipper; dog"},{"front":"legfontosabb","back":"leading; staple; prime"},{"front":"mely","back":"which"},{"front":"basszus","back":"bass"},{"front":"részeg","back":"sloshed; to be bust; to be topped"},{"front":"lát","back":"to pick up; to ken; to descry"},{"front":"friss","back":"crisp; recent; beany"},{"front":"elmegy","back":"to go forth; to go away; to resort"},{"front":"katona","back":"enlisted man; grabby; twink"},{"front":"zene","back":"music"},{"front":"másodperc","back":"second"},{"front":"kellemes","back":"merry; attractive; pleasing"},{"front":"kép","back":"sketch; representation; image"},{"front":"apró","back":"ducky; puny; fine"},{"front":"ördög","back":"fiend; auld horny; father of lies"},{"front":"ügyes","back":"expert; sleek; knowing"},{"front":"azonban","back":"nevertheless; however; after all"},{"front":"kormány","back":"ministerial team; cabinet; wheel"},{"front":"véletlen","back":"promiscuous; hap; contingent"},{"front":"ribanc","back":"polecat; bang; bimbo"},{"front":"belső","back":"intrinsic; landlocked; landward"},{"front":"óvatos","back":"conservative; cagey; guarded"},{"front":"állat","back":"brute; animal; beast"},{"front":"jobbra","back":"to the right; right"},{"front":"kiváló","back":"crack; outstanding; distinguished"},{"front":"esély","back":"chance; odds"},{"front":"további","back":"other; further; additional"},{"front":"indul","back":"to commence; to start"},{"front":"közé","back":"betwixt; amongst; among"},{"front":"mindkét","back":"either"},{"front":"szoba","back":"room; apartment; closet"},{"front":"darab","back":"head; piece; play"},{"front":"sikerül","back":"to fare; to manage; to click"},{"front":"hátul","back":"astern; aft; up-stage"},{"front":"bármelyik","back":"either; any; odd"},{"front":"függ","back":"to depend; to hinge; to hang"},{"front":"magányos","back":"lonesome; solitary; cloistered"},{"front":"mocskos","back":"smudged; damn; sordid"},{"front":"katonai","back":"military"},{"front":"törvény","back":"law; enactment; torach"},{"front":"hagy","back":"to allow of"},{"front":"messzire","back":"away; way back; afar off"},{"front":"hazugság","back":"lie; cracker; prevarication"},{"front":"fajta","back":"assortment; class; tribe"},{"front":"rendesen","back":"regularly; tidily; trimly"},{"front":"természetes","back":"axiomatic; artless; genial"},{"front":"nemrég","back":"lately; just now; recently"},{"front":"elfoglalt","back":"engrossed; to be swamped; busy"},{"front":"bátor","back":"mettled; brave; gritty"},{"front":"balra","back":"leftwards; leftward; aport"},{"front":"zsaruk","back":"fuzz"},{"front":"felelős","back":"answerable; accountable; responsible"},{"front":"durva","back":"barbaric; boorish; insensible"},{"front":"ország","back":"country; clime; land"},{"front":"francia","back":"gaul; froggy; french"},{"front":"alszik","back":"to lie dormant; to doss; to kip"},{"front":"cserébe","back":"in exchange"},{"front":"szeretett","back":"beloved"},{"front":"hazudik","back":"to bull; to utter falsehoods"}]},{"level":"b2","name":"Hungarian B2 · 300 common words","source":"freq+freedict","cards":[{"front":"reggeli","back":"morning; breakfast; déjeuner"},{"front":"telt","back":"full; replete; rich"},{"front":"totál","back":"flat-out"},{"front":"simán","back":"smooth; slick; sleekly"},{"front":"legutóbb","back":"newly; recently"},{"front":"őrnagy","back":"major"},{"front":"rakás","back":"pile; clump; junk"},{"front":"tanár","back":"don; master; teacher"},{"front":"üveg","back":"glass; flask; bottle"},{"front":"hercegnő","back":"princess; duchess"},{"front":"amennyire","back":"insofar as; as"},{"front":"hív","back":"to invoke; to clepe; to get in"},{"front":"kisebb","back":"minor; less; lesser"},{"front":"kínos","back":"grating; untoward; disagreeable"},{"front":"sehol","back":"anywhere; no place; nowhere"},{"front":"féltékeny","back":"yellow; jealous"},{"front":"sehova","back":"no place; nowhere"},{"front":"szexi","back":"hot; sexy; luscious"},{"front":"ír","back":"to pen; unction; salve"},{"front":"pokol","back":"deuce; shades; nether world"},{"front":"különbség","back":"difference; odds; distinction"},{"front":"ruha","back":"clothes; habit; dress"},{"front":"közelében","back":"by"},{"front":"döntés","back":"verdict; resolution; judgement"},{"front":"nagyjából","back":"upon the whole; broadly; broadly speaking"},{"front":"kamera","back":"camera; motion-picture camera"},{"front":"menő","back":"pro; goer; ace"},{"front":"máshol","back":"elsewhere; in another place"},{"front":"egység","back":"one; unity; point"},{"front":"talál","back":"to get home; to hit; to pick up"},{"front":"park","back":"park; gardens"},{"front":"föl","back":"skimmings"},{"front":"orosz","back":"russian"},{"front":"másképp","back":"otherwise; other"},{"front":"körbe","back":"round"},{"front":"ágyban","back":"abed"},{"front":"tisztán","back":"fair; lucidly; legibly"},{"front":"erősen","back":"like a lion; forcefully; viciously"},{"front":"semmiség","back":"counter; nothingness; nothing"},{"front":"múlik","back":"to elapse; to go by; to roll by"},{"front":"szerencse","back":"bit of luck; piece of luck; scoop"},{"front":"barom","back":"simp; beast; schmo"},{"front":"ismeretlen","back":"unknown; faceless; unnamed"},{"front":"keresett","back":"wanted; mannered; prissy"},{"front":"idős","back":"old"},{"front":"bomba","back":"bomb"},{"front":"amiatt","back":"thence"},{"front":"romantikus","back":"romantic"},{"front":"mélyen","back":"sore; thoughtfully; deep"},{"front":"szánalmas","back":"woeful; lamentable; abject"},{"front":"hang","back":"note; speech; strain"},{"front":"akiknek","back":"whom"},{"front":"kulcs","back":"peg; key; clue"},{"front":"tény","back":"fact; deed; reality"},{"front":"egyesült","back":"incorporated; conjugate; incorporate"},{"front":"német","back":"germanic; teuton; hun"},{"front":"próbál","back":"to fit on; to practise; to rehearse"},{"front":"erő","back":"zip; nerve; moment"},{"front":"idáig","back":"so far; thus far"},{"front":"csoport","back":"wing; band; section"},{"front":"akárcsak","back":"the same as; same as"},{"front":"jóképű","back":"good-looking; handsome; have good looks"},{"front":"gyakorlatilag","back":"virtually; in effect; practically"},{"front":"valamikor","back":"at one time; some time ago; sometime"},{"front":"barátnője","back":"his best girl"},{"front":"szövetségi","back":"federal; federate"},{"front":"gyermek","back":"bairn; chip; wean"},{"front":"üzenet","back":"word; message"},{"front":"követ","back":"deputy; envoy; to pursue"},{"front":"izé","back":"what-d`ya-call-it; whatsit; whatchmacallit"},{"front":"atya","back":"begetter; governor; father"},{"front":"futás","back":"bolt; course; scud"},{"front":"borzalmas","back":"scary; gruesome; dire"},{"front":"mindegyik","back":"every one; each"},{"front":"kézzel","back":"by hand"},{"front":"utóbbi","back":"ulterior; latter; late"},{"front":"csúnya","back":"ugly; plain; black"},{"front":"benneteket","back":"ye"},{"front":"fájdalom","back":"dolor; gip; grief"},{"front":"hivatalosan","back":"ex officio; formally"},{"front":"izgatott","back":"wrought-up; to be flurried; fazed"},{"front":"helyesen","back":"rightly; duly; correctly"},{"front":"használt","back":"hand-me-down; used"},{"front":"irány","back":"drift; way; tenor"},{"front":"valamiféle","back":"of a kind"},{"front":"illik","back":"to beseem; to behove; to match"},{"front":"izgalmas","back":"thrilling; hairy-assed; gripping"},{"front":"manapság","back":"in these days; these days; in our days"},{"front":"amerika","back":"god`s own country; god`s country"},{"front":"végső","back":"last-ditch; finishing; supreme"},{"front":"szív","back":"to sup; heart; bosom"},{"front":"parti","back":"freak-out; coastal; party"},{"front":"kétlem","back":"i doubt it"},{"front":"házasság","back":"wedlock; hymen; married life"},{"front":"elveszett","back":"lorn; gone; undone"},{"front":"íme","back":"lo"},{"front":"levegő","back":"wind; ullage; air"},{"front":"errefelé","back":"this way; that way; hereabout"},{"front":"profi","back":"professional; pro; whiz"},{"front":"rendkívül","back":"exceedingly; exceptionally; mighty"},{"front":"évad","back":"season"},{"front":"hadsereg","back":"military; power; army"},{"front":"harc","back":"striving; bout; battle"},{"front":"hiába","back":"to no end; without avail; for nothing"},{"front":"kiderül","back":"to turn out; to light; to fine"},{"front":"mellette","back":"pro"},{"front":"szokásos","back":"habitual; customary; accustomed"},{"front":"egyértelmű","back":"unequivocal; clean-cut; express"},{"front":"húsz","back":"twenty; score"},{"front":"ősi","back":"pristine; ancient; original"},{"front":"hajrá","back":"run-in; spurt; finish"},{"front":"ellenség","back":"enemy; adversary; foe"},{"front":"mód","back":"manner; fashion; style"},{"front":"töltött","back":"stuffed"},{"front":"átlagos","back":"common; run; ordinary"},{"front":"nehezen","back":"hard; with difficulty"},{"front":"vén","back":"old"},{"front":"parancs","back":"behest; injunction; fiat"},{"front":"épület","back":"construction; edifice; building"},{"front":"körülbelül","back":"about; something like; some"},{"front":"csakis","back":"none but; alone"},{"front":"utca","back":"street"},{"front":"korai","back":"early; precocious; untimely"},{"front":"őrültség","back":"lunacy; insanity"},{"front":"test","back":"torso; body; shell"},{"front":"többször","back":"often; on several occasions; on divers occasions"},{"front":"királyi","back":"royal; sceptred; kingly"},{"front":"vasárnap","back":"sabbath; lord`s day; sunday"},{"front":"felirat","back":"petition; title; label"},{"front":"egyikük","back":"one of them"},{"front":"dal","back":"charm; chanson; air"},{"front":"célpont","back":"bourn; objective; mark"},{"front":"pontos","back":"strait; punctual; correct"},{"front":"öregem","back":"old chap"},{"front":"móka","back":"jollity; drollery; jest"},{"front":"egészséges","back":"fit; whole; incorrupt"},{"front":"hajón","back":"by sea; aboard ship; aboard"},{"front":"királynő","back":"queen; queen regnant"},{"front":"valamelyik","back":"some; either of them; either"},{"front":"fa","back":"tree; timber; lumber"},{"front":"sikeres","back":"prosperous; successful; auspicious"},{"front":"határozottan","back":"decidedly; firmly; starkly"},{"front":"politikai","back":"political"},{"front":"amitől","back":"whereby"},{"front":"esküvő","back":"nuptials; hymen; wedding"},{"front":"okoz","back":"to provoke; to inflict; to induce"},{"front":"nyitott","back":"open-air; roofless; open"},{"front":"fenn","back":"up; aloft; astir"},{"front":"gyanúsított","back":"suspect"},{"front":"buta","back":"dull; brainless; stupid"},{"front":"százados","back":"captain; cap"},{"front":"idősebb","back":"elder; major; senior"},{"front":"mellesleg","back":"obiter; on the margin; by the way"},{"front":"sült","back":"done; fry; roast"},{"front":"hasonlít","back":"to come near; to bear resemblance; to be near"},{"front":"későn","back":"tardily; belatedly; late"},{"front":"szabály","back":"convention; precept; observance"},{"front":"házas","back":"wedlock-bound; married"},{"front":"büdös","back":"nifty; smelly; effing"},{"front":"közelben","back":"near at hand; about; at hand"},{"front":"japán","back":"nipponese; japon; japan"},{"front":"megteszi","back":"that will do"},{"front":"körülmények","back":"footing; circumstances"},{"front":"szem","back":"orb; bud; eye"},{"front":"halottak","back":"dead"},{"front":"megérkezett","back":"to be in"},{"front":"pohár","back":"cup; glass"},{"front":"nyugodt","back":"unimpassioned; staid; soft"},{"front":"néni","back":"dame"},{"front":"visszajön","back":"to come again; to come back; to return"},{"front":"kávé","back":"java; coffee"},{"front":"egyben","back":"whole; in one block; in gross"},{"front":"nélküli","back":"void"},{"front":"vak","back":"sightless; blind; dry"},{"front":"magán","back":"unprofessional"},{"front":"cucc","back":"things; doings; clobber"},{"front":"állítólag","back":"reportedly; allegedly; reputedly"},{"front":"golyó","back":"stone; ball; shot"},{"front":"sürgős","back":"express; immediate; acute"},{"front":"teli","back":"fraught; replete; full"},{"front":"verseny","back":"race; competition; pull"},{"front":"kövér","back":"podgy; beefy; plump"},{"front":"ifjú","back":"youngster; lad; stripling"},{"front":"szörnyeteg","back":"monstrosity; harpy; monstruosity"},{"front":"tanács","back":"advisement; council; tip"},{"front":"öngyilkos","back":"suicide; self-destroyer"},{"front":"hírek","back":"news bulletin; advices; news"},{"front":"étel","back":"victuals; meal; scran"},{"front":"béna","back":"crippled; spastic; maimed"},{"front":"méltó","back":"worthy"},{"front":"doboz","back":"tap; carrier; can"},{"front":"alak","back":"figure; cod; shape"},{"front":"kórház","back":"infirmary; hospital"},{"front":"felvétel","back":"enrolment; footing; enrollment"},{"front":"megjött","back":"to be in"},{"front":"amelyik","back":"which"},{"front":"eső","back":"falling; rain; cadent"},{"front":"ismerős","back":"familiar; acquaintance"},{"front":"kaja","back":"grub; tommy; scarf"},{"front":"származik","back":"to derive; to originate; to result"},{"front":"érdemes","back":"to worth while; meritorious; worthwhile"},{"front":"korábbi","back":"preceding; antecedent; previous"},{"front":"banda","back":"band; set; covey"},{"front":"idén","back":"the year"},{"front":"isteni","back":"divvy; aces; divine"},{"front":"baromság","back":"cock"},{"front":"értékes","back":"of high value; golden; rich"},{"front":"következik","back":"to follow; to ensue; to result"},{"front":"jogi","back":"judicial; judiciary; legal"},{"front":"disznó","back":"swine; hog; pig"},{"front":"lefelé","back":"down; down the line; downward"},{"front":"polgármester","back":"provost; mayor"},{"front":"nagyapa","back":"grandfather; grandpa"},{"front":"érthető","back":"plain; luminous; understandable"},{"front":"központ","back":"main branch; central; headquarters"},{"front":"harcos","back":"fighter; militant; combative"},{"front":"tolvaj","back":"scrounge; filch; taker"},{"front":"gyáva","back":"faint-hearted; craven; weak-hearted"},{"front":"szerencsére","back":"blissfully; fortunately; luckily"},{"front":"érkezik","back":"to fetch up; to get in"},{"front":"holtan","back":"dead"},{"front":"edző","back":"hardener; quencher; trainer"},{"front":"megfelel","back":"to gibe; to fit; good enough"},{"front":"halad","back":"to make way; to get on; to progress"},{"front":"telik","back":"to waste; to lapse away; to roll on"},{"front":"levél","back":"epistle; billet; flag"},{"front":"napi","back":"circadian; daily; day"},{"front":"dupla","back":"duplex; double; dual"},{"front":"választás","back":"option; alternative; election"},{"front":"hazug","back":"mendacious; untrue"},{"front":"sérült","back":"injured; casualty; traumatic"},{"front":"csendes","back":"low; serene; still"},{"front":"régebben","back":"formerly"},{"front":"kitűnő","back":"capital; straight as; prize"},{"front":"fizet","back":"to contribute; to stump up; to remit"},{"front":"egek","back":"celestial sphere"},{"front":"fej","back":"to squeeze; upper story; nab"},{"front":"állam","back":"body politic; realm; state"},{"front":"anyag","back":"stuff; body; material"},{"front":"szokatlan","back":"outlandish; unfamiliar; unwonted"},{"front":"ahova","back":"whither; whereto"},{"front":"múltkor","back":"recently"},{"front":"erőszak","back":"outrage; violation; force"},{"front":"sehová","back":"anywhere"},{"front":"hotel","back":"hotel"},{"front":"hold","back":"lamp; satellite; yoke"},{"front":"kellemetlen","back":"trying; ungrateful; awkward"},{"front":"figyel","back":"to hearken; to regard; to harken"},{"front":"megtiszteltetés","back":"honor; honour"},{"front":"zsidó","back":"yid; israelite; judaical"},{"front":"sárga","back":"sallow; amber; yellow"},{"front":"mindenféle","back":"all sorts of; of all kinds; of all sorts"},{"front":"alól","back":"from under; under"},{"front":"nemzeti","back":"national; vernacular"},{"front":"negatív","back":"negative"},{"front":"valószínű","back":"probable; likely; presumptive"},{"front":"szeretet","back":"love; loving-kindness; liking"},{"front":"akkoriban","back":"in those days"},{"front":"titok","back":"secret; privacy"},{"front":"köcsög","back":"jar; jug"},{"front":"hármas","back":"troika; tern; ternary"},{"front":"vezetett","back":"guided"},{"front":"stimmel","back":"to square"},{"front":"kölcsön","back":"loan; advance; borrowing"},{"front":"lord","back":"lord"},{"front":"illegális","back":"illegal"},{"front":"állami","back":"state"},{"front":"háromszor","back":"three times; thrice"},{"front":"aggódik","back":"to feel uncomfortable; to fear; to dread"},{"front":"alacsony","back":"short; low; shallow"},{"front":"szenátor","back":"senator"},{"front":"elkezdett","back":"rough-hewn"},{"front":"hívás","back":"calling; call"},{"front":"klub","back":"club"},{"front":"lélek","back":"psyche; ghost; spirit"},{"front":"ló","back":"hoss; bronco; horse"},{"front":"csupa","back":"all"},{"front":"olcsó","back":"cheap; rinky-dink; budget-priced"},{"front":"egyfajta","back":"a sort of"},{"front":"öröm","back":"gratification; delight; pleasure"},{"front":"leginkább","back":"principally"},{"front":"lopott","back":"furtive; hot"},{"front":"erőszakos","back":"dictatorial; overbearing; bullying"},{"front":"feleség","back":"missus; rib; better half"},{"front":"tilos","back":"not allowed; close"},{"front":"vihar","back":"hurricane wind; drift; tempest"},{"front":"félig","back":"semi-; parcel; half"},{"front":"kegyetlen","back":"barbarous; wolfish; ruthless"},{"front":"eszik","back":"to break bread; to scarf; to stomach"},{"front":"használ","back":"to apply; to ply; to exert"},{"front":"nehezebb","back":"more difficult"},{"front":"ritka","back":"sparse; thin; unwonted"},{"front":"ahonnan","back":"where from; from whence; whence"},{"front":"egyértelműen","back":"squarely; unequivocally"},{"front":"csend","back":"calm; quiet; quietude"},{"front":"karácsony","back":"nativity; festive season"},{"front":"bűnöző","back":"goon; miscreant; offender"},{"front":"kettes","back":"two"},{"front":"ámen","back":"amen"},{"front":"beszéd","back":"manner of speech; tongue; speech"}]}]